rolling_quantiles-1.1.0.dist-info/top_level.txt
rolling_quantiles-1.1.0.dist-info/zip-safe
rolling_quantiles-1.1.0.dist-info/METADATA
rolling_quantiles-1.1.0.dist-info/WHEEL
rolling_quantiles-1.1.0.dist-info/RECORD
rolling_quantiles-1.1.0.dist-info/LICENSE
rolling_quantiles/triton.cpython-38-x86_64-linux-gnu.so
rolling_quantiles/__init__.py
