Metadata-Version: 2.1
Name: rolling-quantiles
Version: 1.1.0
Summary: Composable and blazing fast rolling-quantile filters for streaming data and bulk batches.
Home-page: https://github.com/marmarelis/rolling-quantiles
Author: Myrl Marmarelis
Author-email: myrl@marmarel.is
Keywords: numpy,filter,numeric,signal,streaming,scipy,quantiles,rolling,efficient,realtime
Requires-Python: >=3.7
License-File: ../LICENSE
Requires-Dist: numpy (~=1.20)
